devd/__about__.py
devd/__init__.py
devd/__main__.py
devd/cli/__init__.py
devd-0.1.0.dev1.dist-info/METADATA
devd-0.1.0.dev1.dist-info/WHEEL
devd-0.1.0.dev1.dist-info/entry_points.txt
devd-0.1.0.dev1.dist-info/licenses/LICENSE.txt
devd-0.1.0.dev1.dist-info/RECORD
